whisperer.py
Whisperer-0.2.0.dist-info/METADATA
Whisperer-0.2.0.dist-info/RECORD
Whisperer-0.2.0.dist-info/WHEEL
Whisperer-0.2.0.dist-info/entry_points.txt
Whisperer-0.2.0.dist-info/top_level.txt
