Metadata-Version: 2.1
Name: Whisperer
Version: 0.2.0
Summary: UNKNOWN
Home-page: UNKNOWN
Author: zhangbinhui
Author-email: UNKNOWN
License: UNKNOWN
Platform: UNKNOWN
Requires-Dist: Click
Requires-Dist: markdown2
Requires-Dist: python-gitlab
